iot_protocols/__init__.py
iot_protocols/data.py
iot_protocols/devices/__init__.py
iot_protocols/devices/basics.py
iot_protocols/devices/iec62056_meter.py
iot_protocols/devices/interfaces.py
iot_protocols/devices/models.py
iot_protocols/devices/moxa_iologik_r1214.py
iot_protocols/devices/socomec.py
iot_protocols/protocols/__init__.py
iot_protocols/protocols/iec62056/__init__.py
iot_protocols/protocols/iec62056/client.py
iot_protocols/protocols/iec62056/exceptions.py
iot_protocols/protocols/iec62056/tools/__init__.py
iot_protocols/protocols/iec62056/tools/client.py
iot_protocols/protocols/iec62056/tools/constants.py
iot_protocols/protocols/iec62056/tools/exceptions.py
iot_protocols/protocols/iec62056/tools/messages.py
iot_protocols/protocols/iec62056/tools/transports.py
iot_protocols/protocols/iec62056/tools/utils.py
iot_protocols/protocols/modbus/__init__.py
iot_protocols/protocols/modbus/client.py
iot_protocols/protocols/modbus/decoder.py
iot_protocols/protocols/modbus/exceptions.py
iot_protocols/protocols/modbus/requests.py
iot_protocols/protocols/snap7/__init__.py
iot_protocols/protocols/snap7/client.py
iot_protocols/protocols/snap7/exceptions.py
iot_protocols/protocols/snap7/requests.py
iot_protocols/protocols/snap7/responses.py
iot_protocols-2.1.0.2.dist-info/LICENSE
iot_protocols-2.1.0.2.dist-info/METADATA
iot_protocols-2.1.0.2.dist-info/WHEEL
iot_protocols-2.1.0.2.dist-info/top_level.txt
iot_protocols-2.1.0.2.dist-info/RECORD
