Metadata-Version: 2.1
Name: iot-protocols
Version: 2.1.0.2
Summary: Generic IIoT protocols package
Author-email: Adrien Delhaye <adrien.delhaye@memoco.eu>
Project-URL: Homepage, https://pypi.org/manage/project/iot-protocols
Keywords: python,iiot,protocols
Classifier: Intended Audience :: Developers
Classifier: Programming Language :: Python :: 3.7
Classifier: Operating System :: MacOS :: MacOS X
Classifier: Operating System :: Microsoft :: Windows
Classifier: Operating System :: POSIX :: Linux
Requires-Python: >=3.7
License-File: LICENSE
Requires-Dist: pyserial >=3.5
Requires-Dist: pymodbus ==2.5.3
Requires-Dist: python-snap7 ==1.3
Requires-Dist: multipledispatch ==1.0.0
